MANIFEST.in
README.rst
setup.py
docs/HISTORY.txt
docs/LICENSE.GPL
docs/LICENSE.txt
docs/content-stats-view.png
ftw/__init__.py
ftw.contentstats.egg-info/PKG-INFO
ftw.contentstats.egg-info/SOURCES.txt
ftw.contentstats.egg-info/dependency_links.txt
ftw.contentstats.egg-info/entry_points.txt
ftw.contentstats.egg-info/namespace_packages.txt
ftw.contentstats.egg-info/not-zip-safe
ftw.contentstats.egg-info/requires.txt
ftw.contentstats.egg-info/top_level.txt
ftw/contentstats/__init__.py
ftw/contentstats/command.py
ftw/contentstats/configure.zcml
ftw/contentstats/console.py
ftw/contentstats/disk_usage.py
ftw/contentstats/interfaces.py
ftw/contentstats/logger.py
ftw/contentstats/stats.py
ftw/contentstats/testing.py
ftw/contentstats/utils.py
ftw/contentstats/Extensions/__init__.py
ftw/contentstats/Extensions/install.py
ftw/contentstats/browser/__init__.py
ftw/contentstats/browser/configure.zcml
ftw/contentstats/browser/content_stats.py
ftw/contentstats/browser/dump_stats.py
ftw/contentstats/browser/resources/c3.min.css
ftw/contentstats/browser/resources/c3.min.js
ftw/contentstats/browser/resources/content-stats.css
ftw/contentstats/browser/resources/content-stats.js
ftw/contentstats/browser/resources/d3.v3.min.js
ftw/contentstats/browser/templates/content_stats.pt
ftw/contentstats/demo/__init__.py
ftw/contentstats/demo/configure.zcml
ftw/contentstats/demo/filters.py
ftw/contentstats/profiles/default/metadata.xml
ftw/contentstats/profiles/uninstall/.gitkeep
ftw/contentstats/providers/__init__.py
ftw/contentstats/providers/configure.zcml
ftw/contentstats/providers/disk_usage.py
ftw/contentstats/providers/perf_metrics.py
ftw/contentstats/providers/portal_types.py
ftw/contentstats/providers/review_states.py
ftw/contentstats/tests/__init__.py
ftw/contentstats/tests/test_content_stats_view.py
ftw/contentstats/tests/test_disk_usage.py
ftw/contentstats/tests/test_disk_usage_provider.py
ftw/contentstats/tests/test_dump_stats_view.py
ftw/contentstats/tests/test_logger.py
ftw/contentstats/tests/test_perf_metrics_provider.py
ftw/contentstats/tests/test_portal_types_provider.py
ftw/contentstats/tests/test_profiles.py
ftw/contentstats/tests/test_review_state_provider.py
ftw/contentstats/tests/test_stats.py
ftw/contentstats/tests/test_uninstall.py
ftw/contentstats/tests/assets/__init__.py
