Metadata-Version: 2.1
Name: ftw.contentstats
Version: 1.4.0
Summary: Collect and display content statistics for Plone sites
Home-page: https://github.com/4teamwork/ftw.contentstats
Author: 4teamwork AG
Author-email: mailto:info@4teamwork.ch
License: GPL2
Keywords: ftw content stats statistics
Classifier: Framework :: Plone
Classifier: Framework :: Plone :: 4.3
Classifier: Framework :: Plone :: 5.1
Classifier: License :: OSI Approved :: GNU General Public License (GPL)
Classifier: Programming Language :: Python
Classifier: Programming Language :: Python :: 2.7
Classifier: Topic :: Software Development :: Libraries :: Python Modules
Requires-Dist: Plone
Requires-Dist: Products.CMFCore
Requires-Dist: Products.CMFPlone
Requires-Dist: Products.GenericSetup
Requires-Dist: plone.api
Requires-Dist: setuptools
Requires-Dist: zope.i18nmessageid
Requires-Dist: tzlocal
Requires-Dist: pytz
Requires-Dist: requests
Requires-Dist: path.py>=6.2
Requires-Dist: fluent-logger
Provides-Extra: tests
Requires-Dist: ftw.builder; extra == "tests"
Requires-Dist: ftw.testbrowser; extra == "tests"
Requires-Dist: ftw.testing; extra == "tests"
Requires-Dist: mock; extra == "tests"
Requires-Dist: plone.app.testing; extra == "tests"
Requires-Dist: plone.testing; extra == "tests"
Requires-Dist: plone.app.contenttypes; extra == "tests"
Requires-Dist: transaction; extra == "tests"
Requires-Dist: zope.configuration; extra == "tests"
Requires-Dist: freezegun<0.3.15; extra == "tests"
Requires-Dist: requests_toolbelt; extra == "tests"
Provides-Extra: scandir
Requires-Dist: scandir; extra == "scandir"
